{"id": 737854221, "node_id": "R_kgDOK_rDDQ", "name": "JobJet", "full_name": "elmerdema/JobJet", "private": false, "owner": {"login": "elmerdema", "id": 113256997, "node_id": "U_kgDOBsAqJQ", "avatar_url": "https://avatars.githubusercontent.com/u/113256997?v=4", "gravatar_id": "", "url": "https://api.github.com/users/elmerdema", "html_url": "https://github.com/elmerdema", "followers_url": "https://api.github.com/users/elmerdema/followers", "following_url": "https://api.github.com/users/elmerdema/following{/other_user}", "gists_url": "https://api.github.com/users/elmerdema/gists{/gist_id}", "starred_url": "https://api.github.com/users/elmerdema/starred{/owner}{/repo}", "subscriptions_url": "https://api.github.com/users/elmerdema/subscriptions", "organizations_url": "https://api.github.com/users/elmerdema/orgs", "repos_url": "https://api.github.com/users/elmerdema/repos", "events_url": "https://api.github.com/users/elmerdema/events{/privacy}", "received_events_url": "https://api.github.com/users/elmerdema/received_events", "type": "User", "user_view_type": "public", "site_admin": false}, "html_url": "https://github.com/elmerdema/JobJet", "description": null, "fork": false, "url": "https://api.github.com/repos/elmerdema/JobJet", "forks_url": "https://api.github.com/repos/elmerdema/JobJet/forks", "keys_url": "https://api.github.com/repos/elmerdema/JobJet/keys{/key_id}", "collaborators_url": "https://api.github.com/repos/elmerdema/JobJet/collaborators{/collaborator}", "teams_url": "https://api.github.com/repos/elmerdema/JobJet/teams", "hooks_url": "https://api.github.com/repos/elmerdema/JobJet/hooks", "issue_events_url": "https://api.github.com/repos/elmerdema/JobJet/issues/events{/number}", "events_url": "https://api.github.com/repos/elmerdema/JobJet/events", "assignees_url": "https://api.github.com/repos/elmerdema/JobJet/assignees{/user}", "branches_url": "https://api.github.com/repos/elmerdema/JobJet/branches{/branch}", "tags_url": "https://api.github.com/repos/elmerdema/JobJet/tags", "blobs_url": "https://api.github.com/repos/elmerdema/JobJet/git/blobs{/sha}", "git_tags_url": "https://api.github.com/repos/elmerdema/JobJet/git/tags{/sha}", "git_refs_url": "https://api.github.com/repos/elmerdema/JobJet/git/refs{/sha}", "trees_url": "https://api.github.com/repos/elmerdema/JobJet/git/trees{/sha}", "statuses_url": "https://api.github.com/repos/elmerdema/JobJet/statuses/{sha}", "languages_url": "https://api.github.com/repos/elmerdema/JobJet/languages", "stargazers_url": "https://api.github.com/repos/elmerdema/JobJet/stargazers", "contributors_url": "https://api.github.com/repos/elmerdema/JobJet/contributors", "subscribers_url": "https://api.github.com/repos/elmerdema/JobJet/subscribers", "subscription_url": "https://api.github.com/repos/elmerdema/JobJet/subscription", "commits_url": "https://api.github.com/repos/elmerdema/JobJet/commits{/sha}", "git_commits_url": "https://api.github.com/repos/elmerdema/JobJet/git/commits{/sha}", "comments_url": "https://api.github.com/repos/elmerdema/JobJet/comments{/number}", "issue_comment_url": "https://api.github.com/repos/elmerdema/JobJet/issues/comments{/number}", "contents_url": "https://api.github.com/repos/elmerdema/JobJet/contents/{+path}", "compare_url": "https://api.github.com/repos/elmerdema/JobJet/compare/{base}...{head}", "merges_url": "https://api.github.com/repos/elmerdema/JobJet/merges", "archive_url": "https://api.github.com/repos/elmerdema/JobJet/{archive_format}{/ref}", "downloads_url": "https://api.github.com/repos/elmerdema/JobJet/downloads", "issues_url": "https://api.github.com/repos/elmerdema/JobJet/issues{/number}", "pulls_url": "https://api.github.com/repos/elmerdema/JobJet/pulls{/number}", "milestones_url": "https://api.github.com/repos/elmerdema/JobJet/milestones{/number}", "notifications_url": "https://api.github.com/repos/elmerdema/JobJet/notifications{?since,all,participating}", "labels_url": "https://api.github.com/repos/elmerdema/JobJet/labels{/name}", "releases_url": "https://api.github.com/repos/elmerdema/JobJet/releases{/id}", "deployments_url": "https://api.github.com/repos/elmerdema/JobJet/deployments", "created_at": "2024-01-01T18:29:34Z", "updated_at": "2024-01-01T18:37:17Z", "pushed_at": "2024-01-01T19:19:30Z", "git_url": "git://github.com/elmerdema/JobJet.git", "ssh_url": "git@github.com:elmerdema/JobJet.git", "clone_url": "https://github.com/elmerdema/JobJet.git", "svn_url": "https://github.com/elmerdema/JobJet", "homepage": null, "size": 36, "stargazers_count": 0, "watchers_count": 0, "language": "Python", "has_issues": true, "has_projects": true, "has_downloads": true, "has_wiki": true, "has_pages": false, "has_discussions": false, "forks_count": 0, "mirror_url": null, "archived": false, "disabled": false, "open_issues_count": 0, "license": null, "allow_forking": true, "is_template": false, "web_commit_signoff_required": false, "topics": [], "visibility": "public", "forks": 0, "open_issues": 0, "watchers": 0, "default_branch": "main", "permissions": {"admin": false, "maintain": false, "push": false, "triage": false, "pull": true}, "score": 1.0}