{"id": 817271217, "node_id": "R_kgDOMLaRsQ", "name": "Chatbot_usingRasa", "full_name": "Inshan/Chatbot_usingRasa", "private": false, "owner": {"login": "Inshan", "id": 8745319, "node_id": "MDQ6VXNlcjg3NDUzMTk=", "avatar_url": "https://avatars.githubusercontent.com/u/8745319?v=4", "gravatar_id": "", "url": "https://api.github.com/users/Inshan", "html_url": "https://github.com/Inshan", "followers_url": "https://api.github.com/users/Inshan/followers", "following_url": "https://api.github.com/users/Inshan/following{/other_user}", "gists_url": "https://api.github.com/users/Inshan/gists{/gist_id}", "starred_url": "https://api.github.com/users/Inshan/starred{/owner}{/repo}", "subscriptions_url": "https://api.github.com/users/Inshan/subscriptions", "organizations_url": "https://api.github.com/users/Inshan/orgs", "repos_url": "https://api.github.com/users/Inshan/repos", "events_url": "https://api.github.com/users/Inshan/events{/privacy}", "received_events_url": "https://api.github.com/users/Inshan/received_events", "type": "User", "user_view_type": "public", "site_admin": false}, "html_url": "https://github.com/Inshan/Chatbot_usingRasa", "description": null, "fork": false, "url": "https://api.github.com/repos/Inshan/Chatbot_usingRasa", "forks_url": "https://api.github.com/repos/Inshan/Chatbot_usingRasa/forks", "keys_url": "https://api.github.com/repos/Inshan/Chatbot_usingRasa/keys{/key_id}", "collaborators_url": "https://api.github.com/repos/Inshan/Chatbot_usingRasa/collaborators{/collaborator}", "teams_url": "https://api.github.com/repos/Inshan/Chatbot_usingRasa/teams", "hooks_url": "https://api.github.com/repos/Inshan/Chatbot_usingRasa/hooks", "issue_events_url": "https://api.github.com/repos/Inshan/Chatbot_usingRasa/issues/events{/number}", "events_url": "https://api.github.com/repos/Inshan/Chatbot_usingRasa/events", "assignees_url": "https://api.github.com/repos/Inshan/Chatbot_usingRasa/assignees{/user}", "branches_url": "https://api.github.com/repos/Inshan/Chatbot_usingRasa/branches{/branch}", "tags_url": "https://api.github.com/repos/Inshan/Chatbot_usingRasa/tags", "blobs_url": "https://api.github.com/repos/Inshan/Chatbot_usingRasa/git/blobs{/sha}", "git_tags_url": "https://api.github.com/repos/Inshan/Chatbot_usingRasa/git/tags{/sha}", "git_refs_url": "https://api.github.com/repos/Inshan/Chatbot_usingRasa/git/refs{/sha}", "trees_url": "https://api.github.com/repos/Inshan/Chatbot_usingRasa/git/trees{/sha}", "statuses_url": "https://api.github.com/repos/Inshan/Chatbot_usingRasa/statuses/{sha}", "languages_url": "https://api.github.com/repos/Inshan/Chatbot_usingRasa/languages", "stargazers_url": "https://api.github.com/repos/Inshan/Chatbot_usingRasa/stargazers", "contributors_url": "https://api.github.com/repos/Inshan/Chatbot_usingRasa/contributors", "subscribers_url": "https://api.github.com/repos/Inshan/Chatbot_usingRasa/subscribers", "subscription_url": "https://api.github.com/repos/Inshan/Chatbot_usingRasa/subscription", "commits_url": "https://api.github.com/repos/Inshan/Chatbot_usingRasa/commits{/sha}", "git_commits_url": "https://api.github.com/repos/Inshan/Chatbot_usingRasa/git/commits{/sha}", "comments_url": "https://api.github.com/repos/Inshan/Chatbot_usingRasa/comments{/number}", "issue_comment_url": "https://api.github.com/repos/Inshan/Chatbot_usingRasa/issues/comments{/number}", "contents_url": "https://api.github.com/repos/Inshan/Chatbot_usingRasa/contents/{+path}", "compare_url": "https://api.github.com/repos/Inshan/Chatbot_usingRasa/compare/{base}...{head}", "merges_url": "https://api.github.com/repos/Inshan/Chatbot_usingRasa/merges", "archive_url": "https://api.github.com/repos/Inshan/Chatbot_usingRasa/{archive_format}{/ref}", "downloads_url": "https://api.github.com/repos/Inshan/Chatbot_usingRasa/downloads", "issues_url": "https://api.github.com/repos/Inshan/Chatbot_usingRasa/issues{/number}", "pulls_url": "https://api.github.com/repos/Inshan/Chatbot_usingRasa/pulls{/number}", "milestones_url": "https://api.github.com/repos/Inshan/Chatbot_usingRasa/milestones{/number}", "notifications_url": "https://api.github.com/repos/Inshan/Chatbot_usingRasa/notifications{?since,all,participating}", "labels_url": "https://api.github.com/repos/Inshan/Chatbot_usingRasa/labels{/name}", "releases_url": "https://api.github.com/repos/Inshan/Chatbot_usingRasa/releases{/id}", "deployments_url": "https://api.github.com/repos/Inshan/Chatbot_usingRasa/deployments", "created_at": "2024-06-19T11:10:11Z", "updated_at": "2024-06-19T11:15:13Z", "pushed_at": "2024-06-19T11:15:10Z", "git_url": "git://github.com/Inshan/Chatbot_usingRasa.git", "ssh_url": "git@github.com:Inshan/Chatbot_usingRasa.git", "clone_url": "https://github.com/Inshan/Chatbot_usingRasa.git", "svn_url": "https://github.com/Inshan/Chatbot_usingRasa", "homepage": null, "size": 73268, "stargazers_count": 0, "watchers_count": 0, "language": "Python", "has_issues": true, "has_projects": true, "has_downloads": true, "has_wiki": true, "has_pages": false, "has_discussions": false, "forks_count": 0, "mirror_url": null, "archived": false, "disabled": false, "open_issues_count": 0, "license": null, "allow_forking": true, "is_template": false, "web_commit_signoff_required": false, "topics": [], "visibility": "public", "forks": 0, "open_issues": 0, "watchers": 0, "default_branch": "main", "permissions": {"admin": false, "maintain": false, "push": false, "triage": false, "pull": true}, "score": 1.0}