{"id": 449207941, "node_id": "R_kgDOGsZehQ", "name": "rasaX", "full_name": "jpark2111/rasaX", "private": false, "owner": {"login": "jpark2111", "id": 66935310, "node_id": "MDQ6VXNlcjY2OTM1MzEw", "avatar_url": "https://avatars.githubusercontent.com/u/66935310?v=4", "gravatar_id": "", "url": "https://api.github.com/users/jpark2111", "html_url": "https://github.com/jpark2111", "followers_url": "https://api.github.com/users/jpark2111/followers", "following_url": "https://api.github.com/users/jpark2111/following{/other_user}", "gists_url": "https://api.github.com/users/jpark2111/gists{/gist_id}", "starred_url": "https://api.github.com/users/jpark2111/starred{/owner}{/repo}", "subscriptions_url": "https://api.github.com/users/jpark2111/subscriptions", "organizations_url": "https://api.github.com/users/jpark2111/orgs", "repos_url": "https://api.github.com/users/jpark2111/repos", "events_url": "https://api.github.com/users/jpark2111/events{/privacy}", "received_events_url": "https://api.github.com/users/jpark2111/received_events", "type": "User", "user_view_type": "public", "site_admin": false}, "html_url": "https://github.com/jpark2111/rasaX", "description": null, "fork": false, "url": "https://api.github.com/repos/jpark2111/rasaX", "forks_url": "https://api.github.com/repos/jpark2111/rasaX/forks", "keys_url": "https://api.github.com/repos/jpark2111/rasaX/keys{/key_id}", "collaborators_url": "https://api.github.com/repos/jpark2111/rasaX/collaborators{/collaborator}", "teams_url": "https://api.github.com/repos/jpark2111/rasaX/teams", "hooks_url": "https://api.github.com/repos/jpark2111/rasaX/hooks", "issue_events_url": "https://api.github.com/repos/jpark2111/rasaX/issues/events{/number}", "events_url": "https://api.github.com/repos/jpark2111/rasaX/events", "assignees_url": "https://api.github.com/repos/jpark2111/rasaX/assignees{/user}", "branches_url": "https://api.github.com/repos/jpark2111/rasaX/branches{/branch}", "tags_url": "https://api.github.com/repos/jpark2111/rasaX/tags", "blobs_url": "https://api.github.com/repos/jpark2111/rasaX/git/blobs{/sha}", "git_tags_url": "https://api.github.com/repos/jpark2111/rasaX/git/tags{/sha}", "git_refs_url": "https://api.github.com/repos/jpark2111/rasaX/git/refs{/sha}", "trees_url": "https://api.github.com/repos/jpark2111/rasaX/git/trees{/sha}", "statuses_url": "https://api.github.com/repos/jpark2111/rasaX/statuses/{sha}", "languages_url": "https://api.github.com/repos/jpark2111/rasaX/languages", "stargazers_url": "https://api.github.com/repos/jpark2111/rasaX/stargazers", "contributors_url": "https://api.github.com/repos/jpark2111/rasaX/contributors", "subscribers_url": "https://api.github.com/repos/jpark2111/rasaX/subscribers", "subscription_url": "https://api.github.com/repos/jpark2111/rasaX/subscription", "commits_url": "https://api.github.com/repos/jpark2111/rasaX/commits{/sha}", "git_commits_url": "https://api.github.com/repos/jpark2111/rasaX/git/commits{/sha}", "comments_url": "https://api.github.com/repos/jpark2111/rasaX/comments{/number}", "issue_comment_url": "https://api.github.com/repos/jpark2111/rasaX/issues/comments{/number}", "contents_url": "https://api.github.com/repos/jpark2111/rasaX/contents/{+path}", "compare_url": "https://api.github.com/repos/jpark2111/rasaX/compare/{base}...{head}", "merges_url": "https://api.github.com/repos/jpark2111/rasaX/merges", "archive_url": "https://api.github.com/repos/jpark2111/rasaX/{archive_format}{/ref}", "downloads_url": "https://api.github.com/repos/jpark2111/rasaX/downloads", "issues_url": "https://api.github.com/repos/jpark2111/rasaX/issues{/number}", "pulls_url": "https://api.github.com/repos/jpark2111/rasaX/pulls{/number}", "milestones_url": "https://api.github.com/repos/jpark2111/rasaX/milestones{/number}", "notifications_url": "https://api.github.com/repos/jpark2111/rasaX/notifications{?since,all,participating}", "labels_url": "https://api.github.com/repos/jpark2111/rasaX/labels{/name}", "releases_url": "https://api.github.com/repos/jpark2111/rasaX/releases{/id}", "deployments_url": "https://api.github.com/repos/jpark2111/rasaX/deployments", "created_at": "2022-01-18T08:50:13Z", "updated_at": "2022-01-18T09:05:24Z", "pushed_at": "2023-07-12T04:51:36Z", "git_url": "git://github.com/jpark2111/rasaX.git", "ssh_url": "git@github.com:jpark2111/rasaX.git", "clone_url": "https://github.com/jpark2111/rasaX.git", "svn_url": "https://github.com/jpark2111/rasaX", "homepage": null, "size": 2596, "stargazers_count": 0, "watchers_count": 0, "language": "Python", "has_issues": true, "has_projects": true, "has_downloads": true, "has_wiki": true, "has_pages": false, "has_discussions": false, "forks_count": 0, "mirror_url": null, "archived": false, "disabled": false, "open_issues_count": 0, "license": {"key": "apache-2.0", "name": "Apache License 2.0", "spdx_id": "Apache-2.0", "url": "https://api.github.com/licenses/apache-2.0", "node_id": "MDc6TGljZW5zZTI="}, "allow_forking": true, "is_template": false, "web_commit_signoff_required": false, "topics": [], "visibility": "public", "forks": 0, "open_issues": 0, "watchers": 0, "default_branch": "main", "permissions": {"admin": false, "maintain": false, "push": false, "triage": false, "pull": true}, "score": 1.0}