{"id": 191295315, "node_id": "MDEwOlJlcG9zaXRvcnkxOTEyOTUzMTU=", "name": "rasa-nrj", "full_name": "linyisen1985/rasa-nrj", "private": false, "owner": {"login": "linyisen1985", "id": 25973177, "node_id": "MDQ6VXNlcjI1OTczMTc3", "avatar_url": "https://avatars.githubusercontent.com/u/25973177?v=4", "gravatar_id": "", "url": "https://api.github.com/users/linyisen1985", "html_url": "https://github.com/linyisen1985", "followers_url": "https://api.github.com/users/linyisen1985/followers", "following_url": "https://api.github.com/users/linyisen1985/following{/other_user}", "gists_url": "https://api.github.com/users/linyisen1985/gists{/gist_id}", "starred_url": "https://api.github.com/users/linyisen1985/starred{/owner}{/repo}", "subscriptions_url": "https://api.github.com/users/linyisen1985/subscriptions", "organizations_url": "https://api.github.com/users/linyisen1985/orgs", "repos_url": "https://api.github.com/users/linyisen1985/repos", "events_url": "https://api.github.com/users/linyisen1985/events{/privacy}", "received_events_url": "https://api.github.com/users/linyisen1985/received_events", "type": "User", "user_view_type": "public", "site_admin": false}, "html_url": "https://github.com/linyisen1985/rasa-nrj", "description": "chatbot for nrj", "fork": false, "url": "https://api.github.com/repos/linyisen1985/rasa-nrj", "forks_url": "https://api.github.com/repos/linyisen1985/rasa-nrj/forks", "keys_url": "https://api.github.com/repos/linyisen1985/rasa-nrj/keys{/key_id}", "collaborators_url": "https://api.github.com/repos/linyisen1985/rasa-nrj/collaborators{/collaborator}", "teams_url": "https://api.github.com/repos/linyisen1985/rasa-nrj/teams", "hooks_url": "https://api.github.com/repos/linyisen1985/rasa-nrj/hooks", "issue_events_url": "https://api.github.com/repos/linyisen1985/rasa-nrj/issues/events{/number}", "events_url": "https://api.github.com/repos/linyisen1985/rasa-nrj/events", "assignees_url": "https://api.github.com/repos/linyisen1985/rasa-nrj/assignees{/user}", "branches_url": "https://api.github.com/repos/linyisen1985/rasa-nrj/branches{/branch}", "tags_url": "https://api.github.com/repos/linyisen1985/rasa-nrj/tags", "blobs_url": "https://api.github.com/repos/linyisen1985/rasa-nrj/git/blobs{/sha}", "git_tags_url": "https://api.github.com/repos/linyisen1985/rasa-nrj/git/tags{/sha}", "git_refs_url": "https://api.github.com/repos/linyisen1985/rasa-nrj/git/refs{/sha}", "trees_url": "https://api.github.com/repos/linyisen1985/rasa-nrj/git/trees{/sha}", "statuses_url": "https://api.github.com/repos/linyisen1985/rasa-nrj/statuses/{sha}", "languages_url": "https://api.github.com/repos/linyisen1985/rasa-nrj/languages", "stargazers_url": "https://api.github.com/repos/linyisen1985/rasa-nrj/stargazers", "contributors_url": "https://api.github.com/repos/linyisen1985/rasa-nrj/contributors", "subscribers_url": "https://api.github.com/repos/linyisen1985/rasa-nrj/subscribers", "subscription_url": "https://api.github.com/repos/linyisen1985/rasa-nrj/subscription", "commits_url": "https://api.github.com/repos/linyisen1985/rasa-nrj/commits{/sha}", "git_commits_url": "https://api.github.com/repos/linyisen1985/rasa-nrj/git/commits{/sha}", "comments_url": "https://api.github.com/repos/linyisen1985/rasa-nrj/comments{/number}", "issue_comment_url": "https://api.github.com/repos/linyisen1985/rasa-nrj/issues/comments{/number}", "contents_url": "https://api.github.com/repos/linyisen1985/rasa-nrj/contents/{+path}", "compare_url": "https://api.github.com/repos/linyisen1985/rasa-nrj/compare/{base}...{head}", "merges_url": "https://api.github.com/repos/linyisen1985/rasa-nrj/merges", "archive_url": "https://api.github.com/repos/linyisen1985/rasa-nrj/{archive_format}{/ref}", "downloads_url": "https://api.github.com/repos/linyisen1985/rasa-nrj/downloads", "issues_url": "https://api.github.com/repos/linyisen1985/rasa-nrj/issues{/number}", "pulls_url": "https://api.github.com/repos/linyisen1985/rasa-nrj/pulls{/number}", "milestones_url": "https://api.github.com/repos/linyisen1985/rasa-nrj/milestones{/number}", "notifications_url": "https://api.github.com/repos/linyisen1985/rasa-nrj/notifications{?since,all,participating}", "labels_url": "https://api.github.com/repos/linyisen1985/rasa-nrj/labels{/name}", "releases_url": "https://api.github.com/repos/linyisen1985/rasa-nrj/releases{/id}", "deployments_url": "https://api.github.com/repos/linyisen1985/rasa-nrj/deployments", "created_at": "2019-06-11T04:44:01Z", "updated_at": "2019-06-11T04:46:16Z", "pushed_at": "2019-06-11T04:46:15Z", "git_url": "git://github.com/linyisen1985/rasa-nrj.git", "ssh_url": "git@github.com:linyisen1985/rasa-nrj.git", "clone_url": "https://github.com/linyisen1985/rasa-nrj.git", "svn_url": "https://github.com/linyisen1985/rasa-nrj", "homepage": null, "size": 3, "stargazers_count": 0, "watchers_count": 0, "language": "Python", "has_issues": true, "has_projects": true, "has_downloads": true, "has_wiki": true, "has_pages": false, "has_discussions": false, "forks_count": 0, "mirror_url": null, "archived": false, "disabled": false, "open_issues_count": 0, "license": null, "allow_forking": true, "is_template": false, "web_commit_signoff_required": false, "topics": [], "visibility": "public", "forks": 0, "open_issues": 0, "watchers": 0, "default_branch": "master", "permissions": {"admin": false, "maintain": false, "push": false, "triage": false, "pull": true}, "score": 1.0}