{"id": 167792945, "node_id": "MDEwOlJlcG9zaXRvcnkxNjc3OTI5NDU=", "name": "bot", "full_name": "Mayukhmaity/bot", "private": false, "owner": {"login": "Mayukhmaity", "id": 34765548, "node_id": "MDQ6VXNlcjM0NzY1NTQ4", "avatar_url": "https://avatars.githubusercontent.com/u/34765548?v=4", "gravatar_id": "", "url": "https://api.github.com/users/Mayukhmaity", "html_url": "https://github.com/Mayukhmaity", "followers_url": "https://api.github.com/users/Mayukhmaity/followers", "following_url": "https://api.github.com/users/Mayukhmaity/following{/other_user}", "gists_url": "https://api.github.com/users/Mayukhmaity/gists{/gist_id}", "starred_url": "https://api.github.com/users/Mayukhmaity/starred{/owner}{/repo}", "subscriptions_url": "https://api.github.com/users/Mayukhmaity/subscriptions", "organizations_url": "https://api.github.com/users/Mayukhmaity/orgs", "repos_url": "https://api.github.com/users/Mayukhmaity/repos", "events_url": "https://api.github.com/users/Mayukhmaity/events{/privacy}", "received_events_url": "https://api.github.com/users/Mayukhmaity/received_events", "type": "User", "user_view_type": "public", "site_admin": false}, "html_url": "https://github.com/Mayukhmaity/bot", "description": "created chatbot using rasa framework", "fork": false, "url": "https://api.github.com/repos/Mayukhmaity/bot", "forks_url": "https://api.github.com/repos/Mayukhmaity/bot/forks", "keys_url": "https://api.github.com/repos/Mayukhmaity/bot/keys{/key_id}", "collaborators_url": "https://api.github.com/repos/Mayukhmaity/bot/collaborators{/collaborator}", "teams_url": "https://api.github.com/repos/Mayukhmaity/bot/teams", "hooks_url": "https://api.github.com/repos/Mayukhmaity/bot/hooks", "issue_events_url": "https://api.github.com/repos/Mayukhmaity/bot/issues/events{/number}", "events_url": "https://api.github.com/repos/Mayukhmaity/bot/events", "assignees_url": "https://api.github.com/repos/Mayukhmaity/bot/assignees{/user}", "branches_url": "https://api.github.com/repos/Mayukhmaity/bot/branches{/branch}", "tags_url": "https://api.github.com/repos/Mayukhmaity/bot/tags", "blobs_url": "https://api.github.com/repos/Mayukhmaity/bot/git/blobs{/sha}", "git_tags_url": "https://api.github.com/repos/Mayukhmaity/bot/git/tags{/sha}", "git_refs_url": "https://api.github.com/repos/Mayukhmaity/bot/git/refs{/sha}", "trees_url": "https://api.github.com/repos/Mayukhmaity/bot/git/trees{/sha}", "statuses_url": "https://api.github.com/repos/Mayukhmaity/bot/statuses/{sha}", "languages_url": "https://api.github.com/repos/Mayukhmaity/bot/languages", "stargazers_url": "https://api.github.com/repos/Mayukhmaity/bot/stargazers", "contributors_url": "https://api.github.com/repos/Mayukhmaity/bot/contributors", "subscribers_url": "https://api.github.com/repos/Mayukhmaity/bot/subscribers", "subscription_url": "https://api.github.com/repos/Mayukhmaity/bot/subscription", "commits_url": "https://api.github.com/repos/Mayukhmaity/bot/commits{/sha}", "git_commits_url": "https://api.github.com/repos/Mayukhmaity/bot/git/commits{/sha}", "comments_url": "https://api.github.com/repos/Mayukhmaity/bot/comments{/number}", "issue_comment_url": "https://api.github.com/repos/Mayukhmaity/bot/issues/comments{/number}", "contents_url": "https://api.github.com/repos/Mayukhmaity/bot/contents/{+path}", "compare_url": "https://api.github.com/repos/Mayukhmaity/bot/compare/{base}...{head}", "merges_url": "https://api.github.com/repos/Mayukhmaity/bot/merges", "archive_url": "https://api.github.com/repos/Mayukhmaity/bot/{archive_format}{/ref}", "downloads_url": "https://api.github.com/repos/Mayukhmaity/bot/downloads", "issues_url": "https://api.github.com/repos/Mayukhmaity/bot/issues{/number}", "pulls_url": "https://api.github.com/repos/Mayukhmaity/bot/pulls{/number}", "milestones_url": "https://api.github.com/repos/Mayukhmaity/bot/milestones{/number}", "notifications_url": "https://api.github.com/repos/Mayukhmaity/bot/notifications{?since,all,participating}", "labels_url": "https://api.github.com/repos/Mayukhmaity/bot/labels{/name}", "releases_url": "https://api.github.com/repos/Mayukhmaity/bot/releases{/id}", "deployments_url": "https://api.github.com/repos/Mayukhmaity/bot/deployments", "created_at": "2019-01-27T09:48:49Z", "updated_at": "2020-07-11T06:09:26Z", "pushed_at": "2019-01-27T09:55:54Z", "git_url": "git://github.com/Mayukhmaity/bot.git", "ssh_url": "git@github.com:Mayukhmaity/bot.git", "clone_url": "https://github.com/Mayukhmaity/bot.git", "svn_url": "https://github.com/Mayukhmaity/bot", "homepage": null, "size": 119, "stargazers_count": 0, "watchers_count": 0, "language": "Python", "has_issues": true, "has_projects": true, "has_downloads": true, "has_wiki": true, "has_pages": false, "has_discussions": false, "forks_count": 0, "mirror_url": null, "archived": false, "disabled": false, "open_issues_count": 0, "license": null, "allow_forking": true, "is_template": false, "web_commit_signoff_required": false, "topics": [], "visibility": "public", "forks": 0, "open_issues": 0, "watchers": 0, "default_branch": "master", "permissions": {"admin": false, "maintain": false, "push": false, "triage": false, "pull": true}, "score": 1.0}