{"id": 206222984, "node_id": "MDEwOlJlcG9zaXRvcnkyMDYyMjI5ODQ=", "name": "NLP-zoo", "full_name": "ningshixian/NLP-zoo", "private": false, "owner": {"login": "ningshixian", "id": 9280395, "node_id": "MDQ6VXNlcjkyODAzOTU=", "avatar_url": "https://avatars.githubusercontent.com/u/9280395?v=4", "gravatar_id": "", "url": "https://api.github.com/users/ningshixian", "html_url": "https://github.com/ningshixian", "followers_url": "https://api.github.com/users/ningshixian/followers", "following_url": "https://api.github.com/users/ningshixian/following{/other_user}", "gists_url": "https://api.github.com/users/ningshixian/gists{/gist_id}", "starred_url": "https://api.github.com/users/ningshixian/starred{/owner}{/repo}", "subscriptions_url": "https://api.github.com/users/ningshixian/subscriptions", "organizations_url": "https://api.github.com/users/ningshixian/orgs", "repos_url": "https://api.github.com/users/ningshixian/repos", "events_url": "https://api.github.com/users/ningshixian/events{/privacy}", "received_events_url": "https://api.github.com/users/ningshixian/received_events", "type": "User", "user_view_type": "public", "site_admin": false}, "html_url": "https://github.com/ningshixian/NLP-zoo", "description": "nlp related resources+all kinds of tutorials \u4e2d\u6587\u81ea\u7136\u8bed\u8a00\u5904\u7406\u76f8\u5173\u8d44\u6599", "fork": false, "url": "https://api.github.com/repos/ningshixian/NLP-zoo", "forks_url": "https://api.github.com/repos/ningshixian/NLP-zoo/forks", "keys_url": "https://api.github.com/repos/ningshixian/NLP-zoo/keys{/key_id}", "collaborators_url": "https://api.github.com/repos/ningshixian/NLP-zoo/collaborators{/collaborator}", "teams_url": "https://api.github.com/repos/ningshixian/NLP-zoo/teams", "hooks_url": "https://api.github.com/repos/ningshixian/NLP-zoo/hooks", "issue_events_url": "https://api.github.com/repos/ningshixian/NLP-zoo/issues/events{/number}", "events_url": "https://api.github.com/repos/ningshixian/NLP-zoo/events", "assignees_url": "https://api.github.com/repos/ningshixian/NLP-zoo/assignees{/user}", "branches_url": "https://api.github.com/repos/ningshixian/NLP-zoo/branches{/branch}", "tags_url": "https://api.github.com/repos/ningshixian/NLP-zoo/tags", "blobs_url": "https://api.github.com/repos/ningshixian/NLP-zoo/git/blobs{/sha}", "git_tags_url": "https://api.github.com/repos/ningshixian/NLP-zoo/git/tags{/sha}", "git_refs_url": "https://api.github.com/repos/ningshixian/NLP-zoo/git/refs{/sha}", "trees_url": "https://api.github.com/repos/ningshixian/NLP-zoo/git/trees{/sha}", "statuses_url": "https://api.github.com/repos/ningshixian/NLP-zoo/statuses/{sha}", "languages_url": "https://api.github.com/repos/ningshixian/NLP-zoo/languages", "stargazers_url": "https://api.github.com/repos/ningshixian/NLP-zoo/stargazers", "contributors_url": "https://api.github.com/repos/ningshixian/NLP-zoo/contributors", "subscribers_url": "https://api.github.com/repos/ningshixian/NLP-zoo/subscribers", "subscription_url": "https://api.github.com/repos/ningshixian/NLP-zoo/subscription", "commits_url": "https://api.github.com/repos/ningshixian/NLP-zoo/commits{/sha}", "git_commits_url": "https://api.github.com/repos/ningshixian/NLP-zoo/git/commits{/sha}", "comments_url": "https://api.github.com/repos/ningshixian/NLP-zoo/comments{/number}", "issue_comment_url": "https://api.github.com/repos/ningshixian/NLP-zoo/issues/comments{/number}", "contents_url": "https://api.github.com/repos/ningshixian/NLP-zoo/contents/{+path}", "compare_url": "https://api.github.com/repos/ningshixian/NLP-zoo/compare/{base}...{head}", "merges_url": "https://api.github.com/repos/ningshixian/NLP-zoo/merges", "archive_url": "https://api.github.com/repos/ningshixian/NLP-zoo/{archive_format}{/ref}", "downloads_url": "https://api.github.com/repos/ningshixian/NLP-zoo/downloads", "issues_url": "https://api.github.com/repos/ningshixian/NLP-zoo/issues{/number}", "pulls_url": "https://api.github.com/repos/ningshixian/NLP-zoo/pulls{/number}", "milestones_url": "https://api.github.com/repos/ningshixian/NLP-zoo/milestones{/number}", "notifications_url": "https://api.github.com/repos/ningshixian/NLP-zoo/notifications{?since,all,participating}", "labels_url": "https://api.github.com/repos/ningshixian/NLP-zoo/labels{/name}", "releases_url": "https://api.github.com/repos/ningshixian/NLP-zoo/releases{/id}", "deployments_url": "https://api.github.com/repos/ningshixian/NLP-zoo/deployments", "created_at": "2019-09-04T03:27:17Z", "updated_at": "2024-01-02T03:32:45Z", "pushed_at": "2020-10-09T07:42:11Z", "git_url": "git://github.com/ningshixian/NLP-zoo.git", "ssh_url": "git@github.com:ningshixian/NLP-zoo.git", "clone_url": "https://github.com/ningshixian/NLP-zoo.git", "svn_url": "https://github.com/ningshixian/NLP-zoo", "homepage": "", "size": 14405, "stargazers_count": 8, "watchers_count": 8, "language": "Jupyter Notebook", "has_issues": true, "has_projects": true, "has_downloads": true, "has_wiki": true, "has_pages": false, "has_discussions": false, "forks_count": 0, "mirror_url": null, "archived": false, "disabled": false, "open_issues_count": 1, "license": null, "allow_forking": true, "is_template": false, "web_commit_signoff_required": false, "topics": [], "visibility": "public", "forks": 0, "open_issues": 1, "watchers": 8, "default_branch": "master", "permissions": {"admin": false, "maintain": false, "push": false, "triage": false, "pull": true}, "score": 1.0}