{"id": 186609622, "node_id": "MDEwOlJlcG9zaXRvcnkxODY2MDk2MjI=", "name": "rasa_nlu-0.14.6", "full_name": "rbossie/rasa_nlu-0.14.6", "private": false, "owner": {"login": "rbossie", "id": 50572012, "node_id": "MDQ6VXNlcjUwNTcyMDEy", "avatar_url": "https://avatars.githubusercontent.com/u/50572012?v=4", "gravatar_id": "", "url": "https://api.github.com/users/rbossie", "html_url": "https://github.com/rbossie", "followers_url": "https://api.github.com/users/rbossie/followers", "following_url": "https://api.github.com/users/rbossie/following{/other_user}", "gists_url": "https://api.github.com/users/rbossie/gists{/gist_id}", "starred_url": "https://api.github.com/users/rbossie/starred{/owner}{/repo}", "subscriptions_url": "https://api.github.com/users/rbossie/subscriptions", "organizations_url": "https://api.github.com/users/rbossie/orgs", "repos_url": "https://api.github.com/users/rbossie/repos", "events_url": "https://api.github.com/users/rbossie/events{/privacy}", "received_events_url": "https://api.github.com/users/rbossie/received_events", "type": "User", "user_view_type": "public", "site_admin": false}, "html_url": "https://github.com/rbossie/rasa_nlu-0.14.6", "description": null, "fork": false, "url": "https://api.github.com/repos/rbossie/rasa_nlu-0.14.6", "forks_url": "https://api.github.com/repos/rbossie/rasa_nlu-0.14.6/forks", "keys_url": "https://api.github.com/repos/rbossie/rasa_nlu-0.14.6/keys{/key_id}", "collaborators_url": "https://api.github.com/repos/rbossie/rasa_nlu-0.14.6/collaborators{/collaborator}", "teams_url": "https://api.github.com/repos/rbossie/rasa_nlu-0.14.6/teams", "hooks_url": "https://api.github.com/repos/rbossie/rasa_nlu-0.14.6/hooks", "issue_events_url": "https://api.github.com/repos/rbossie/rasa_nlu-0.14.6/issues/events{/number}", "events_url": "https://api.github.com/repos/rbossie/rasa_nlu-0.14.6/events", "assignees_url": "https://api.github.com/repos/rbossie/rasa_nlu-0.14.6/assignees{/user}", "branches_url": "https://api.github.com/repos/rbossie/rasa_nlu-0.14.6/branches{/branch}", "tags_url": "https://api.github.com/repos/rbossie/rasa_nlu-0.14.6/tags", "blobs_url": "https://api.github.com/repos/rbossie/rasa_nlu-0.14.6/git/blobs{/sha}", "git_tags_url": "https://api.github.com/repos/rbossie/rasa_nlu-0.14.6/git/tags{/sha}", "git_refs_url": "https://api.github.com/repos/rbossie/rasa_nlu-0.14.6/git/refs{/sha}", "trees_url": "https://api.github.com/repos/rbossie/rasa_nlu-0.14.6/git/trees{/sha}", "statuses_url": "https://api.github.com/repos/rbossie/rasa_nlu-0.14.6/statuses/{sha}", "languages_url": "https://api.github.com/repos/rbossie/rasa_nlu-0.14.6/languages", "stargazers_url": "https://api.github.com/repos/rbossie/rasa_nlu-0.14.6/stargazers", "contributors_url": "https://api.github.com/repos/rbossie/rasa_nlu-0.14.6/contributors", "subscribers_url": "https://api.github.com/repos/rbossie/rasa_nlu-0.14.6/subscribers", "subscription_url": "https://api.github.com/repos/rbossie/rasa_nlu-0.14.6/subscription", "commits_url": "https://api.github.com/repos/rbossie/rasa_nlu-0.14.6/commits{/sha}", "git_commits_url": "https://api.github.com/repos/rbossie/rasa_nlu-0.14.6/git/commits{/sha}", "comments_url": "https://api.github.com/repos/rbossie/rasa_nlu-0.14.6/comments{/number}", "issue_comment_url": "https://api.github.com/repos/rbossie/rasa_nlu-0.14.6/issues/comments{/number}", "contents_url": "https://api.github.com/repos/rbossie/rasa_nlu-0.14.6/contents/{+path}", "compare_url": "https://api.github.com/repos/rbossie/rasa_nlu-0.14.6/compare/{base}...{head}", "merges_url": "https://api.github.com/repos/rbossie/rasa_nlu-0.14.6/merges", "archive_url": "https://api.github.com/repos/rbossie/rasa_nlu-0.14.6/{archive_format}{/ref}", "downloads_url": "https://api.github.com/repos/rbossie/rasa_nlu-0.14.6/downloads", "issues_url": "https://api.github.com/repos/rbossie/rasa_nlu-0.14.6/issues{/number}", "pulls_url": "https://api.github.com/repos/rbossie/rasa_nlu-0.14.6/pulls{/number}", "milestones_url": "https://api.github.com/repos/rbossie/rasa_nlu-0.14.6/milestones{/number}", "notifications_url": "https://api.github.com/repos/rbossie/rasa_nlu-0.14.6/notifications{?since,all,participating}", "labels_url": "https://api.github.com/repos/rbossie/rasa_nlu-0.14.6/labels{/name}", "releases_url": "https://api.github.com/repos/rbossie/rasa_nlu-0.14.6/releases{/id}", "deployments_url": "https://api.github.com/repos/rbossie/rasa_nlu-0.14.6/deployments", "created_at": "2019-05-14T11:37:27Z", "updated_at": "2019-05-21T14:20:54Z", "pushed_at": "2022-10-26T02:13:57Z", "git_url": "git://github.com/rbossie/rasa_nlu-0.14.6.git", "ssh_url": "git@github.com:rbossie/rasa_nlu-0.14.6.git", "clone_url": "https://github.com/rbossie/rasa_nlu-0.14.6.git", "svn_url": "https://github.com/rbossie/rasa_nlu-0.14.6", "homepage": null, "size": 519, "stargazers_count": 0, "watchers_count": 0, "language": "Python", "has_issues": true, "has_projects": true, "has_downloads": true, "has_wiki": true, "has_pages": false, "has_discussions": false, "forks_count": 1, "mirror_url": null, "archived": false, "disabled": false, "open_issues_count": 1, "license": {"key": "apache-2.0", "name": "Apache License 2.0", "spdx_id": "Apache-2.0", "url": "https://api.github.com/licenses/apache-2.0", "node_id": "MDc6TGljZW5zZTI="}, "allow_forking": true, "is_template": false, "web_commit_signoff_required": false, "topics": [], "visibility": "public", "forks": 1, "open_issues": 1, "watchers": 0, "default_branch": "master", "permissions": {"admin": false, "maintain": false, "push": false, "triage": false, "pull": true}, "score": 1.0}