{"id": 89468461, "node_id": "MDEwOlJlcG9zaXRvcnk4OTQ2ODQ2MQ==", "name": "Chatbot", "full_name": "rojinva/Chatbot", "private": false, "owner": {"login": "rojinva", "id": 5328548, "node_id": "MDQ6VXNlcjUzMjg1NDg=", "avatar_url": "https://avatars.githubusercontent.com/u/5328548?v=4", "gravatar_id": "", "url": "https://api.github.com/users/rojinva", "html_url": "https://github.com/rojinva", "followers_url": "https://api.github.com/users/rojinva/followers", "following_url": "https://api.github.com/users/rojinva/following{/other_user}", "gists_url": "https://api.github.com/users/rojinva/gists{/gist_id}", "starred_url": "https://api.github.com/users/rojinva/starred{/owner}{/repo}", "subscriptions_url": "https://api.github.com/users/rojinva/subscriptions", "organizations_url": "https://api.github.com/users/rojinva/orgs", "repos_url": "https://api.github.com/users/rojinva/repos", "events_url": "https://api.github.com/users/rojinva/events{/privacy}", "received_events_url": "https://api.github.com/users/rojinva/received_events", "type": "User", "user_view_type": "public", "site_admin": false}, "html_url": "https://github.com/rojinva/Chatbot", "description": null, "fork": false, "url": "https://api.github.com/repos/rojinva/Chatbot", "forks_url": "https://api.github.com/repos/rojinva/Chatbot/forks", "keys_url": "https://api.github.com/repos/rojinva/Chatbot/keys{/key_id}", "collaborators_url": "https://api.github.com/repos/rojinva/Chatbot/collaborators{/collaborator}", "teams_url": "https://api.github.com/repos/rojinva/Chatbot/teams", "hooks_url": "https://api.github.com/repos/rojinva/Chatbot/hooks", "issue_events_url": "https://api.github.com/repos/rojinva/Chatbot/issues/events{/number}", "events_url": "https://api.github.com/repos/rojinva/Chatbot/events", "assignees_url": "https://api.github.com/repos/rojinva/Chatbot/assignees{/user}", "branches_url": "https://api.github.com/repos/rojinva/Chatbot/branches{/branch}", "tags_url": "https://api.github.com/repos/rojinva/Chatbot/tags", "blobs_url": "https://api.github.com/repos/rojinva/Chatbot/git/blobs{/sha}", "git_tags_url": "https://api.github.com/repos/rojinva/Chatbot/git/tags{/sha}", "git_refs_url": "https://api.github.com/repos/rojinva/Chatbot/git/refs{/sha}", "trees_url": "https://api.github.com/repos/rojinva/Chatbot/git/trees{/sha}", "statuses_url": "https://api.github.com/repos/rojinva/Chatbot/statuses/{sha}", "languages_url": "https://api.github.com/repos/rojinva/Chatbot/languages", "stargazers_url": "https://api.github.com/repos/rojinva/Chatbot/stargazers", "contributors_url": "https://api.github.com/repos/rojinva/Chatbot/contributors", "subscribers_url": "https://api.github.com/repos/rojinva/Chatbot/subscribers", "subscription_url": "https://api.github.com/repos/rojinva/Chatbot/subscription", "commits_url": "https://api.github.com/repos/rojinva/Chatbot/commits{/sha}", "git_commits_url": "https://api.github.com/repos/rojinva/Chatbot/git/commits{/sha}", "comments_url": "https://api.github.com/repos/rojinva/Chatbot/comments{/number}", "issue_comment_url": "https://api.github.com/repos/rojinva/Chatbot/issues/comments{/number}", "contents_url": "https://api.github.com/repos/rojinva/Chatbot/contents/{+path}", "compare_url": "https://api.github.com/repos/rojinva/Chatbot/compare/{base}...{head}", "merges_url": "https://api.github.com/repos/rojinva/Chatbot/merges", "archive_url": "https://api.github.com/repos/rojinva/Chatbot/{archive_format}{/ref}", "downloads_url": "https://api.github.com/repos/rojinva/Chatbot/downloads", "issues_url": "https://api.github.com/repos/rojinva/Chatbot/issues{/number}", "pulls_url": "https://api.github.com/repos/rojinva/Chatbot/pulls{/number}", "milestones_url": "https://api.github.com/repos/rojinva/Chatbot/milestones{/number}", "notifications_url": "https://api.github.com/repos/rojinva/Chatbot/notifications{?since,all,participating}", "labels_url": "https://api.github.com/repos/rojinva/Chatbot/labels{/name}", "releases_url": "https://api.github.com/repos/rojinva/Chatbot/releases{/id}", "deployments_url": "https://api.github.com/repos/rojinva/Chatbot/deployments", "created_at": "2017-04-26T10:26:28Z", "updated_at": "2019-06-11T07:13:48Z", "pushed_at": "2022-12-27T15:01:14Z", "git_url": "git://github.com/rojinva/Chatbot.git", "ssh_url": "git@github.com:rojinva/Chatbot.git", "clone_url": "https://github.com/rojinva/Chatbot.git", "svn_url": "https://github.com/rojinva/Chatbot", "homepage": null, "size": 785, "stargazers_count": 0, "watchers_count": 0, "language": "Python", "has_issues": true, "has_projects": true, "has_downloads": true, "has_wiki": true, "has_pages": false, "has_discussions": false, "forks_count": 1, "mirror_url": null, "archived": false, "disabled": false, "open_issues_count": 5, "license": null, "allow_forking": true, "is_template": false, "web_commit_signoff_required": false, "topics": [], "visibility": "public", "forks": 1, "open_issues": 5, "watchers": 0, "default_branch": "master", "permissions": {"admin": false, "maintain": false, "push": false, "triage": false, "pull": true}, "score": 1.0}