{"id": 450132243, "node_id": "R_kgDOGtR5Ew", "name": "MiAI_PixBot", "full_name": "thangnch/MiAI_PixBot", "private": false, "owner": {"login": "thangnch", "id": 43836831, "node_id": "MDQ6VXNlcjQzODM2ODMx", "avatar_url": "https://avatars.githubusercontent.com/u/43836831?v=4", "gravatar_id": "", "url": "https://api.github.com/users/thangnch", "html_url": "https://github.com/thangnch", "followers_url": "https://api.github.com/users/thangnch/followers", "following_url": "https://api.github.com/users/thangnch/following{/other_user}", "gists_url": "https://api.github.com/users/thangnch/gists{/gist_id}", "starred_url": "https://api.github.com/users/thangnch/starred{/owner}{/repo}", "subscriptions_url": "https://api.github.com/users/thangnch/subscriptions", "organizations_url": "https://api.github.com/users/thangnch/orgs", "repos_url": "https://api.github.com/users/thangnch/repos", "events_url": "https://api.github.com/users/thangnch/events{/privacy}", "received_events_url": "https://api.github.com/users/thangnch/received_events", "type": "User", "user_view_type": "public", "site_admin": false}, "html_url": "https://github.com/thangnch/MiAI_PixBot", "description": "Demo of handle image message in rasa chatbot", "fork": false, "url": "https://api.github.com/repos/thangnch/MiAI_PixBot", "forks_url": "https://api.github.com/repos/thangnch/MiAI_PixBot/forks", "keys_url": "https://api.github.com/repos/thangnch/MiAI_PixBot/keys{/key_id}", "collaborators_url": "https://api.github.com/repos/thangnch/MiAI_PixBot/collaborators{/collaborator}", "teams_url": "https://api.github.com/repos/thangnch/MiAI_PixBot/teams", "hooks_url": "https://api.github.com/repos/thangnch/MiAI_PixBot/hooks", "issue_events_url": "https://api.github.com/repos/thangnch/MiAI_PixBot/issues/events{/number}", "events_url": "https://api.github.com/repos/thangnch/MiAI_PixBot/events", "assignees_url": "https://api.github.com/repos/thangnch/MiAI_PixBot/assignees{/user}", "branches_url": "https://api.github.com/repos/thangnch/MiAI_PixBot/branches{/branch}", "tags_url": "https://api.github.com/repos/thangnch/MiAI_PixBot/tags", "blobs_url": "https://api.github.com/repos/thangnch/MiAI_PixBot/git/blobs{/sha}", "git_tags_url": "https://api.github.com/repos/thangnch/MiAI_PixBot/git/tags{/sha}", "git_refs_url": "https://api.github.com/repos/thangnch/MiAI_PixBot/git/refs{/sha}", "trees_url": "https://api.github.com/repos/thangnch/MiAI_PixBot/git/trees{/sha}", "statuses_url": "https://api.github.com/repos/thangnch/MiAI_PixBot/statuses/{sha}", "languages_url": "https://api.github.com/repos/thangnch/MiAI_PixBot/languages", "stargazers_url": "https://api.github.com/repos/thangnch/MiAI_PixBot/stargazers", "contributors_url": "https://api.github.com/repos/thangnch/MiAI_PixBot/contributors", "subscribers_url": "https://api.github.com/repos/thangnch/MiAI_PixBot/subscribers", "subscription_url": "https://api.github.com/repos/thangnch/MiAI_PixBot/subscription", "commits_url": "https://api.github.com/repos/thangnch/MiAI_PixBot/commits{/sha}", "git_commits_url": "https://api.github.com/repos/thangnch/MiAI_PixBot/git/commits{/sha}", "comments_url": "https://api.github.com/repos/thangnch/MiAI_PixBot/comments{/number}", "issue_comment_url": "https://api.github.com/repos/thangnch/MiAI_PixBot/issues/comments{/number}", "contents_url": "https://api.github.com/repos/thangnch/MiAI_PixBot/contents/{+path}", "compare_url": "https://api.github.com/repos/thangnch/MiAI_PixBot/compare/{base}...{head}", "merges_url": "https://api.github.com/repos/thangnch/MiAI_PixBot/merges", "archive_url": "https://api.github.com/repos/thangnch/MiAI_PixBot/{archive_format}{/ref}", "downloads_url": "https://api.github.com/repos/thangnch/MiAI_PixBot/downloads", "issues_url": "https://api.github.com/repos/thangnch/MiAI_PixBot/issues{/number}", "pulls_url": "https://api.github.com/repos/thangnch/MiAI_PixBot/pulls{/number}", "milestones_url": "https://api.github.com/repos/thangnch/MiAI_PixBot/milestones{/number}", "notifications_url": "https://api.github.com/repos/thangnch/MiAI_PixBot/notifications{?since,all,participating}", "labels_url": "https://api.github.com/repos/thangnch/MiAI_PixBot/labels{/name}", "releases_url": "https://api.github.com/repos/thangnch/MiAI_PixBot/releases{/id}", "deployments_url": "https://api.github.com/repos/thangnch/MiAI_PixBot/deployments", "created_at": "2022-01-20T14:34:54Z", "updated_at": "2024-07-11T15:48:34Z", "pushed_at": "2022-01-21T15:11:33Z", "git_url": "git://github.com/thangnch/MiAI_PixBot.git", "ssh_url": "git@github.com:thangnch/MiAI_PixBot.git", "clone_url": "https://github.com/thangnch/MiAI_PixBot.git", "svn_url": "https://github.com/thangnch/MiAI_PixBot", "homepage": null, "size": 119888, "stargazers_count": 2, "watchers_count": 2, "language": "Python", "has_issues": true, "has_projects": true, "has_downloads": true, "has_wiki": true, "has_pages": false, "has_discussions": false, "forks_count": 0, "mirror_url": null, "archived": false, "disabled": false, "open_issues_count": 0, "license": null, "allow_forking": true, "is_template": false, "web_commit_signoff_required": false, "topics": [], "visibility": "public", "forks": 0, "open_issues": 0, "watchers": 2, "default_branch": "master", "permissions": {"admin": false, "maintain": false, "push": false, "triage": false, "pull": true}, "score": 1.0}