{"id": 344830503, "node_id": "MDEwOlJlcG9zaXRvcnkzNDQ4MzA1MDM=", "name": "chatbot-1-to-2", "full_name": "wechaty/chatbot-1-to-2", "private": false, "owner": {"login": "wechaty", "id": 21285357, "node_id": "MDEyOk9yZ2FuaXphdGlvbjIxMjg1MzU3", "avatar_url": "https://avatars.githubusercontent.com/u/21285357?v=4", "gravatar_id": "", "url": "https://api.github.com/users/wechaty", "html_url": "https://github.com/wechaty", "followers_url": "https://api.github.com/users/wechaty/followers", "following_url": "https://api.github.com/users/wechaty/following{/other_user}", "gists_url": "https://api.github.com/users/wechaty/gists{/gist_id}", "starred_url": "https://api.github.com/users/wechaty/starred{/owner}{/repo}", "subscriptions_url": "https://api.github.com/users/wechaty/subscriptions", "organizations_url": "https://api.github.com/users/wechaty/orgs", "repos_url": "https://api.github.com/users/wechaty/repos", "events_url": "https://api.github.com/users/wechaty/events{/privacy}", "received_events_url": "https://api.github.com/users/wechaty/received_events", "type": "Organization", "user_view_type": "public", "site_admin": false}, "html_url": "https://github.com/wechaty/chatbot-1-to-2", "description": "the source code of chatbot-1-to-2", "fork": false, "url": "https://api.github.com/repos/wechaty/chatbot-1-to-2", "forks_url": "https://api.github.com/repos/wechaty/chatbot-1-to-2/forks", "keys_url": "https://api.github.com/repos/wechaty/chatbot-1-to-2/keys{/key_id}", "collaborators_url": "https://api.github.com/repos/wechaty/chatbot-1-to-2/collaborators{/collaborator}", "teams_url": "https://api.github.com/repos/wechaty/chatbot-1-to-2/teams", "hooks_url": "https://api.github.com/repos/wechaty/chatbot-1-to-2/hooks", "issue_events_url": "https://api.github.com/repos/wechaty/chatbot-1-to-2/issues/events{/number}", "events_url": "https://api.github.com/repos/wechaty/chatbot-1-to-2/events", "assignees_url": "https://api.github.com/repos/wechaty/chatbot-1-to-2/assignees{/user}", "branches_url": "https://api.github.com/repos/wechaty/chatbot-1-to-2/branches{/branch}", "tags_url": "https://api.github.com/repos/wechaty/chatbot-1-to-2/tags", "blobs_url": "https://api.github.com/repos/wechaty/chatbot-1-to-2/git/blobs{/sha}", "git_tags_url": "https://api.github.com/repos/wechaty/chatbot-1-to-2/git/tags{/sha}", "git_refs_url": "https://api.github.com/repos/wechaty/chatbot-1-to-2/git/refs{/sha}", "trees_url": "https://api.github.com/repos/wechaty/chatbot-1-to-2/git/trees{/sha}", "statuses_url": "https://api.github.com/repos/wechaty/chatbot-1-to-2/statuses/{sha}", "languages_url": "https://api.github.com/repos/wechaty/chatbot-1-to-2/languages", "stargazers_url": "https://api.github.com/repos/wechaty/chatbot-1-to-2/stargazers", "contributors_url": "https://api.github.com/repos/wechaty/chatbot-1-to-2/contributors", "subscribers_url": "https://api.github.com/repos/wechaty/chatbot-1-to-2/subscribers", "subscription_url": "https://api.github.com/repos/wechaty/chatbot-1-to-2/subscription", "commits_url": "https://api.github.com/repos/wechaty/chatbot-1-to-2/commits{/sha}", "git_commits_url": "https://api.github.com/repos/wechaty/chatbot-1-to-2/git/commits{/sha}", "comments_url": "https://api.github.com/repos/wechaty/chatbot-1-to-2/comments{/number}", "issue_comment_url": "https://api.github.com/repos/wechaty/chatbot-1-to-2/issues/comments{/number}", "contents_url": "https://api.github.com/repos/wechaty/chatbot-1-to-2/contents/{+path}", "compare_url": "https://api.github.com/repos/wechaty/chatbot-1-to-2/compare/{base}...{head}", "merges_url": "https://api.github.com/repos/wechaty/chatbot-1-to-2/merges", "archive_url": "https://api.github.com/repos/wechaty/chatbot-1-to-2/{archive_format}{/ref}", "downloads_url": "https://api.github.com/repos/wechaty/chatbot-1-to-2/downloads", "issues_url": "https://api.github.com/repos/wechaty/chatbot-1-to-2/issues{/number}", "pulls_url": "https://api.github.com/repos/wechaty/chatbot-1-to-2/pulls{/number}", "milestones_url": "https://api.github.com/repos/wechaty/chatbot-1-to-2/milestones{/number}", "notifications_url": "https://api.github.com/repos/wechaty/chatbot-1-to-2/notifications{?since,all,participating}", "labels_url": "https://api.github.com/repos/wechaty/chatbot-1-to-2/labels{/name}", "releases_url": "https://api.github.com/repos/wechaty/chatbot-1-to-2/releases{/id}", "deployments_url": "https://api.github.com/repos/wechaty/chatbot-1-to-2/deployments", "created_at": "2021-03-05T14:09:29Z", "updated_at": "2021-06-06T05:41:18Z", "pushed_at": "2021-06-06T05:41:15Z", "git_url": "git://github.com/wechaty/chatbot-1-to-2.git", "ssh_url": "git@github.com:wechaty/chatbot-1-to-2.git", "clone_url": "https://github.com/wechaty/chatbot-1-to-2.git", "svn_url": "https://github.com/wechaty/chatbot-1-to-2", "homepage": "https://wechaty.github.io/chatbot-1-to-2/", "size": 1761, "stargazers_count": 1, "watchers_count": 1, "language": "JavaScript", "has_issues": true, "has_projects": true, "has_downloads": true, "has_wiki": true, "has_pages": true, "has_discussions": false, "forks_count": 1, "mirror_url": null, "archived": false, "disabled": false, "open_issues_count": 0, "license": {"key": "apache-2.0", "name": "Apache License 2.0", "spdx_id": "Apache-2.0", "url": "https://api.github.com/licenses/apache-2.0", "node_id": "MDc6TGljZW5zZTI="}, "allow_forking": true, "is_template": false, "web_commit_signoff_required": false, "topics": ["book", "tutorial", "wechaty"], "visibility": "public", "forks": 1, "open_issues": 0, "watchers": 1, "default_branch": "master", "permissions": {"admin": false, "maintain": false, "push": false, "triage": false, "pull": true}, "score": 1.0}